toxinet/__init__.py
toxinet/classifier.py
toxinet/diagnostics.py
toxinet/load_data.py
toxinet/selection.py
toxinet/utils.py
toxinet-0.0.2.dist-info/METADATA
toxinet-0.0.2.dist-info/WHEEL
toxinet-0.0.2.dist-info/licenses/LICENCE
toxinet-0.0.2.dist-info/RECORD
